pycasatunes/__init__.py
pycasatunes/client.py
pycasatunes/const.py
pycasatunes/exceptions.py
pycasatunes/objects/__init__.py
pycasatunes/objects/base.py
pycasatunes/objects/media.py
pycasatunes/objects/nowplaying.py
pycasatunes/objects/source.py
pycasatunes/objects/system.py
pycasatunes/objects/zone.py
pycasatunes-0.1.5.dist-info/METADATA
pycasatunes-0.1.5.dist-info/WHEEL
pycasatunes-0.1.5.dist-info/RECORD
