Metadata-Version: 2.1
Name: pycasatunes
Version: 0.1.5
Summary: Asynchronous python client for CasaTunes.
Home-page: https://github.com/jonkristian/pycasatunes
License: MIT
Keywords: casatunes,multiroom,api,async,client
Author: Jon Kristian Nilsen
Author-email: hello@jonkristian.no
Requires-Python: >=3.8,<4.0
Classifier: License :: OSI Approved :: MIT License
Classifier: Programming Language :: Python :: 3
Classifier: Programming Language :: Python :: 3.8
Classifier: Programming Language :: Python :: 3.9
Classifier: Programming Language :: Python :: 3.10
Classifier: Programming Language :: Python :: 3.11
Requires-Dist: aiohttp (>=3.7.4,<4.0.0)
Project-URL: Documentation, https://github.com/jonkristian/pycasatunes
Project-URL: Repository, https://github.com/jonkristian/pycasatunes
